{
  "updated": null,
  "note": "Auto-generated by .github/workflows/update-feeds.yml. Until the Action runs on GitHub, 'updated' is null and the playbook shows direct links. Run scripts/build_feeds.py locally (with internet) to populate it.",
  "sources": [
    { "key": "mckinsey", "name": "McKinsey Insights", "items": [] },
    { "key": "bcg", "name": "BCG Publications", "items": [] },
    { "key": "hbr", "name": "Harvard Business Review", "items": [] },
    { "key": "hbr_pod", "name": "HBR Podcasts (IdeaCast)", "items": [] },
    { "key": "sloan", "name": "MIT Sloan Management Review", "items": [] },
    { "key": "wharton", "name": "Knowledge at Wharton", "items": [] },
    { "key": "deloitte", "name": "Deloitte Insights", "items": [] }
  ]
}
